README.md
setup.py
holdem/__init__.py
holdem/env.py
holdem/player.py
holdem/utils.py
holdem.egg-info/PKG-INFO
holdem.egg-info/SOURCES.txt
holdem.egg-info/dependency_links.txt
holdem.egg-info/requires.txt
holdem.egg-info/top_level.txt