Metadata-Version: 1.0
Name: holdem
Version: 1.0.0
Summary: OpenAI Gym No-Limit Texas Holdem Environment.
Home-page: https://github.com/wenkesj/holdem
Author: Sam Wenke
Author-email: samwenke@gmail.com
License: MIT
Platform: any
